COPYING
MANIFEST.in
README
README.rst
benchmark.png
setup.py
src/pycephes/__init__.py
src/pycephes/hyper.py
src/pycephes.egg-info/PKG-INFO
src/pycephes.egg-info/SOURCES.txt
src/pycephes.egg-info/dependency_links.txt
src/pycephes.egg-info/requires.txt
src/pycephes.egg-info/top_level.txt