Metadata-Version: 1.0
Name: pycephes
Version: 0.1.0
Summary: Python wrapper for CEPHES using CFFI and numba
Home-page: https://github.com/poliastro/pycephes
Author: Juan Luis Cano
Author-email: hello@juanlu.space
License: UNKNOWN
Platform: UNKNOWN
